dms_recommender/__init__.py
dms_recommender/model/__init__.py
dms_recommender/model/input.py
dms_recommender/model/output.py
dms_recommender/recommender/__init__.py
dms_recommender/recommender/basket_analysis/__init__.py
dms_recommender/recommender/basket_analysis/basket_analysis.py
dms_recommender/recommender/collaborative/__init__.py
dms_recommender/recommender/collaborative/collaborative.py
dms_recommender/recommender/content_based/__init__.py
dms_recommender/recommender/content_based/content_based.py
dms_recommender/recommender/content_based/content_based_orm.py
dms_recommender/recommender/content_based/transtkd_data.csv
dms_recommender/utils/__init__.py
dms_recommender/utils/config.py
dms_recommender-0.1.0.dist-info/WHEEL
dms_recommender-0.1.0.dist-info/METADATA
dms_recommender-0.1.0.dist-info/RECORD
