Metadata-Version: 2.1
Name: dms-recommender
Version: 0.1.0
Summary: A recommendation system
Author: Cream
Author-email: cream.p@gmail.com
Requires-Python: >=3.9,<4.0
Classifier: Programming Language :: Python :: 3
Classifier: Programming Language :: Python :: 3.9
Classifier: Programming Language :: Python :: 3.10
Requires-Dist: numpy (>=1.17,<2.0)
Requires-Dist: pandas (>=2.2.2,<3.0.0)
Requires-Dist: pydantic (>=2.8.2,<3.0.0)
Requires-Dist: scikit-learn (>=1.5.1,<2.0.0)
Requires-Dist: torch (==2.3.1)
Requires-Dist: transformers (>=4.42.4,<5.0.0)
